{"format_version":0,"geometry.Lopunny4D":0,"geometry.TamedWolf":0,"geometry.BlazeBorn":0,"geometry.VBChikaFujiwara":0,"geometry.VBElizabeth":0,"geometry.VBElma":0,"geometry.VBHanaUzaki":0,"geometry.VBRem":0,"geometry.VBRam":0,"geometry.VBZeroTwo":0,"geometry.VBMegumin":0,"geometry.DemonLemon":0,"geometry.Tricky5D":0,"geometry.Flippy5D":0,"geometry.RickSanchez5D":0,"geometry.BoyFriend5D":0,"geometry.ToonLink":0,"geometry.RedKnightCC":0,"geometry.CorruptGolem":0,"geometry.Faputa4DV2":0,"geometry.Flammie4D":0,"geometry.kitsune":0,"geometry.MagnumGuy":0,"geometry.DualGunsChief":0,"geometry.Blaze":0,"geometry.Freezerlaze":0,"geometry.WitherBossAnimated":0,"geometry.spider":0,"geometry.ByDFFArmaduraSuprema":0,"geometry.ByDffPESkinLasConejasDePlaya":0,"geometry.humanoid.custom":0,"geometry.humanoid.customSlim":0,"geometry.ByDFFAmyTheHedgehog":0,"geometry.ByDFFNavidadSkin1":0,"geometry.ByDFFStormtrooperCustom":0,"geometry.CreeperGirlSkinByDFF":0,"geometry.ByDffPESkindeConejas":0,"geometry.ByDFFAudifonos":0,"geometry.D_Flog_Flag_Cinema_5D":0,"geometry.ByDFFSenkoSan":0,"geometry.ByDFFShadowV1":0,"geometry.ByDFFMilitar":0,"geometry.ByDFFCDITDZ":0,"geometry.Halo":0,"geometry.gokuthanos":0,"geometry.LinkByDFlogFlag":0,"geometry.samuraiorobydff":0,"geometry.ByDFFBebeP":0,"geometry.ByDFFBebeF":0,"geometry.ByDFFBebeM":0,"geometry.ByDFFKiara":0,"geometry.ByDFFFaldaP":0,"geometry.ByDFFFalda":0,"geometry.zombieslamacowbydf":0,"geometry.SkeletoDeHuidaSlamaCowByDFF":0,"geometry.EndermanSlamacowbyDFF":0,"geometry.ElReyFallingKingdomByDFF":0,"geometry.LegendaF":0,"geometry.LegendaFA":0,"geometry.InuyashaByDFF":0,"geometry.ByMeD":0,"geometry.legenda":0,"geometry.SlamacowByDFF":0,"geometry.ByDFFWarmachine":0,"geometry.ByDFFAstronauta":0,"geometry.ByDFFSoldadoDeHierro":0,"geometry.ByDFFLanzaDeOro":0,"geometry.ByDFFUmbreon":0,"geometry.CuboRubikByDFF":0,"geometry.conejoF":0,"geometry.conejo":0,"geometry.ByDFFConejoHumanoide2M":0,"geometry.ByDFFConejoHumanoide2F":0,"geometry.ByDFFConejoHumanoide2P":0,"geometry.ByDFFConstructor":0,"geometry.ByDFFSkin4DQuieresUnAbrazo":0,"geometry.ByDFFSkin4DQuieresUnAbrazoF":0,"geometry.ByDFFSkin4DQuieresUnAbrazoP":0,"geometry.1skin":0,"geometry.hey":0,"geometry.inquisidor":0,"geometry.ultragolem":0,"geometry.amyp":0,"geometry.wolflink":0,"geometry.inquisidormx":0,"geometry.granny":0,"geometry.ByDFFLamparaDeDesarrollador":0,"geometry.ByDFFLamparaDeDesarrolladorF":0,"geometry.ByDFFLamparaDeDesarrolladorFP":0,"geometry.blazegirl":0,"geometry.bowsette":0,"geometry.pillagergirl":0,"geometry.snowgolem":0,"geometry.ultrasnowgolem":0,"geometry.a1":0,"geometry.a2":0,"geometry.a3":0,"geometry.a4":0,"geometry.a5":0,"geometry.prawn":1,"geometry.alice":1,"geometry.tnt":1,"geometry.xdg1":1,"geometry.xdg2":1,"geometry.scp999":1,"geometry.oso":1,"geometry.skeletonnew":1,"geometry.pig":1,"geometry.villager":1,"geometry.cow":1,"geometry.horse":1,"geometry.cat":1,"geometry.fox":1,"geometry.inquisidorotaku":1,"geometry.sonic":1,"geometry.netherite":1,"geometry.nose":1,"geometry.pikachu":1,"geometry.booette":1,"geometry.foxgirl":1,"geometry.wandering":1,"geometry.witchgg":1,"geometry.wolfes":1,"geometry.robots":1,"geometry.end":1,"geometry.babyyoda":1,"geometry.komododragon":1,"geometry.wolves":1,"geometry.zombiemutante":1,"geometry.piglin":1,"geometry.zombiepiglin":1,"geometry.bee":1,"geometry.endermanmutante":1,"geometry.hoglin":1,"geometry.rain":1,"geometry.hackers":1,"geometry.rar":1,"geometry.shrekmini":1,"geometry.elizabeth":1,"geometry.finn":1,"geometry.toad":1,"geometry.elite":1,"geometry.diane":1,"geometry.zorrodeusomilitar":1,"geometry.tpose":1,"geometry.zorritadeusomilitar":1,"geometry.zorri":1,"geometry.creeper":1,"geometry.maurisio":1,"geometry.statuecoral":1,"geometry.aldeano0":1,"geometry.aldeano2":1,"geometry.yael2":1,"geometry.marselo":1,"geometry.aldeana":1,"geometry.halomx":1,"geometry.fionna":1,"geometry.cars":1,"geometry.mariosun":1,"geometry.kirby":1,"geometry.link2":1,"geometry.axel":1,"geometry.beebattler":1,"geometry.ncp1":1,"geometry.mre1":1,"geometry.beeboy2":1,"geometry.beeboy3":1,"geometry.grils":1,"geometry.pizzahead":1,"geometry.ncp4":1,"geometry.sharkhead":1,"geometry.corona":1,"geometry.witherstorm":1,"geometry.seamoth":1,"geometry.dffgirl":1,"geometry.ministeve":1,"geometry.anticorona":1,"geometry.bonesmen":1,"geometry.enderdragon":1,"geometry.rtasvadum":1,"geometry.skin4dhd4k":1,"geometry.snowymilitar":1,"geometry.iluminatienderman":1,"geometry.marine":1,"geometry.wings":1,"geometry.skin4d1":1,"geometry.exoesqueleto23":1,"geometry.miligirl":1,"geometry.tofubyloffus":1,"geometry.sebastian":1,"geometry.chicken":1,"geometry.darklink":1,"geometry.ben10":1,"geometry.babys":1,"geometry.meliodas":1,"geometry.turtles":1,"geometry.nether":1,"geometry.undertaker":1,"geometry.cielito":1,"geometry.grell":2,"geometry.zombiec":2,"geometry.gzombie":2,"geometry.ronald":2,"geometry.will":2,"geometry.alois":2,"geometry.asesinodearboles":2,"geometry.peach":2,"geometry.gokumaster":2,"geometry.bruh":2,"geometry.espadadiamante":2,"geometry.monokuma":2,"geometry.cuphead":2,"geometry.pacmanskyrrel":2,"geometry.humanoidshark":2,"geometry.gicathd":2,"geometry.ironsuit":2,"geometry.ashket":2,"geometry.endermansteve":2,"geometry.kreisis":2,"geometry.jokatsu":2,"geometry.minecraftearth":2,"geometry.exoesqueletop":2,"geometry.claireredfield2":2,"geometry.bandicootm":2,"geometry.bandicoot":2,"geometry.lion":2,"geometry.heyrainbow":2,"geometry.lightfury":2,"geometry.khepaso":2,"geometry.circulovirus":2,"geometry.lugimansion":2,"geometry.enderman":2,"geometry.strider":2,"geometry.chen":2,"geometry.idia":2,"geometry.cuora":2,"geometry.exusiai":2,"geometry.joanofarc":2,"geometry.karenaijo":2,"geometry.pajinyi":2,"geometry.demongirl":2,"geometry.komeijikoishi":2,"geometry.konpakuyoumu":2,"geometry.leona":2,"geometry.hakurei":2,"geometry.hutatsuiwamamizou":2,"geometry.imaizumikagerou":2,"geometry.inubashirimomizi":2,"geometry.mes":2,"geometry.kawasironitori":2,"geometry.kazamiyuka":2,"geometry.kitchoyachie":2,"geometry.kochiyasanae":2,"geometry.mima":2,"geometry.murasaminamitsu":2,"geometry.nazrin":2,"geometry.palmita":2,"geometry.hiperhd":2,"geometry.girl4k":2,"geometry.onozukakomachi":2,"geometry.tv":2,"geometry.reisenudongeininaba":2,"geometry.rumia":2,"geometry.saigyoujiyuyuko":2,"geometry.seiran":2,"geometry.sukunashinmyoumaru":2,"geometry.syameimaruaya":2,"geometry.tewiinaba":2,"geometry.toyosatomiminomiko":2,"geometry.tsukumobenben":2,"geometry.daiyousei":2,"geometry.moon":2,"geometry.bees24":2,"geometry.shrek":2,"geometry.hunter":2,"geometry.disimo":2,"geometry.warthogtripulado":2,"geometry.warthog":2,"geometry.si":2,"geometry.skullkid":2,"geometry.toadette":2,"geometry.kingnanatzu":2,"geometry.Deku":2,"geometry.hamburguesa":2,"geometry.daliminigun":2,"geometry.phantom":2,"geometry.broly":2,"geometry.gokussj":2,"geometry.gokussj3":2,"geometry.kratos":2,"geometry.thanosguante":2,"geometry.gokugod":2,"geometry.gokuultradom":2,"geometry.vegetassjblue":2,"geometry.vegeta":2,"geometry.marshmelloled":2,"geometry.sans":2,"geometry.elizabethv1":2,"geometry.hackerlvl1":2,"geometry.stevemamado":3,"geometry.bardock":3,"geometry.todoroki":3,"geometry.tomura":3,"geometry.VnMarvel":3,"geometry.catys":3,"geometry.catysoff":3,"geometry.catysloli":3,"geometry.catyslolioff":3,"geometry.jy":3,"geometry.centinela":3,"geometry.elite1":3,"geometry.jefemaestro":3,"geometry.suilketchup":3,"geometry.golemsupermamado":3,"geometry.nanachi45d":3,"geometry.yoshi":3,"geometry.flygon":3,"geometry.343":3,"geometry.navidadkid":3,"geometry.demogorgon":3,"geometry.scp049":3,"geometry.scp166":3,"geometry.scp250":3,"geometry.pikosarmor":3,"geometry.linkzora":3,"geometry.killerspider":3,"geometry.ganondorf":3,"geometry.malon":3,"geometry.reverse":3,"geometry.malonc":3,"geometry.rayquaza":3,"geometry.goron":3,"geometry.dekulink":3,"geometry.shirakamifubuki":3,"geometry.ibukisuika":3,"geometry.nagitofox":3,"geometry.odst":3,"geometry.amys":3,"geometry.senkosanbymikomamste":3,"geometry.bigsmoke":3,"geometry.flood":3,"geometry.miku":3,"geometry.bobesponja":3,"geometry.groadon":3,"geometry.ghostve":3,"geometry.warthogve":3,"geometry.whatthatsword":3,"geometry.flanbird":3,"geometry.floodh":3,"geometry.dffweapons":3,"geometry.linksysnosxd":3,"geometry.cj":3,"geometry.linkhdweapons":3,"geometry.linkhdweaponsinv":3,"geometry.ironmans":3,"geometry.cybertruck":3,"geometry.raichu":3,"geometry.stormtruper":3,"geometry.grunt":3,"geometry.luffy":3,"geometry.unity":3,"geometry.ellia":3,"geometry.spyro":3,"geometry.Illya":3,"geometry.matsu":3,"geometry.floodcarrier":3,"geometry.madara":3,"geometry.coffindance":3,"geometry.floodin":3,"geometry.cubikrubik":3,"geometry.flammieprever2":3,"geometry.mobs5":3,"geometry.kirby5d":3,"geometry.zelda5d":3,"geometry.sharkheady":3,"geometry.spidermanayauri":3,"geometry.rp3":3,"geometry.vanillarobotgirl":3,"geometry.gold":3,"geometry.creeper3":3,"geometry.flammiever2":3,"geometry.panamiguel":3,"geometry.goldenk4l3b":3,"geometry.valentin":3,"geometry.bonnie":3,"geometry.fredbear":3,"geometry.glitchtrap":3,"geometry.springbonnie":3,"geometry.witheredfoxy":3,"geometry.retro":3,"geometry.Doctor_Pyanco":3,"geometry.nexo_inuyasha_skin":3,"geometry.nexo_inuyasha_skin_empu":3,"geometry.arunda":3,"geometry.irongolem":3,"geometry.chicoconalas":3,"geometry.monsterdroiida":3,"geometry.blokkit":3,"geometry.cuteboyshirt":3,"geometry.coolboy":4,"geometry.thezheri":4,"geometry.floodjuggernaut":4,"geometry.pozoledigoinquisidor":4,"geometry.rem":4,"geometry.zombie":4,"geometry.zombiewithcow":4,"geometry.jefemaestroh2":4,"geometry.stella":4,"geometry.elesistraveler":4,"geometry.skinanimenosequexd":4,"geometry.dffnew":4,"geometry.newdffmaster":4,"geometry.stevefumando":4,"geometry.stevefumandocongorra":4,"geometry.kirara5d":4,"geometry.kekogames":4,"geometry.yoryigamer":4,"geometry.andiuber":4,"geometry.anthonycraft":4,"geometry.davidsuperpig":4,"geometry.eumaster":4,"geometry.itsedu":4,"geometry.jhonprincs":4,"geometry.kernelfreeze":4,"geometry.mikecrack":4,"geometry.sirkael":4,"geometry.theduran":4,"geometry.timba":4,"geometry.trollino":4,"geometry.warfredone":4,"geometry.younglink5D":4,"geometry.cyberconnect2":4,"geometry.pelican":4,"geometry.ahegaof":4,"geometry.ahegaom":4,"geometry.capahd":4,"geometry.patricio":4,"geometry.kirarademon":4,"geometry.pinksheep":4,"geometry.capahd2":4,"geometry.capahd3":4,"geometry.capahd4":4,"geometry.alexfumando":4,"geometry.alexfumandocongorra":4,"geometry.salmon":4,"geometry.vaporeon":4,"geometry.greatdragon":4,"geometry.hdfurryskin":4,"geometry.furryfox":4,"geometry.catearsandtail":4,"geometry.bunnyearsandtail":4,"geometry.angelhornsandwings":4,"geometry.demonhornsandwingsandtail":4,"geometry.cathearsandtail2":4,"geometry.shrek5d":4,"geometry.shrek5dmini":4,"geometry.sprigtrapbysalfontius":4,"geometry.realhdfacef":4,"geometry.jotaro":4,"geometry.monokuma5d":4,"geometry.randomguy":4,"geometry.zheromierda":4,"geometry.flammiever3":4,"geometry.bulbasur":4,"geometry.rango":4,"geometry.konata":4,"geometry.luca":4,"geometry.ElHeroedeOakvaleBySalfontius":4,"geometry.robotito":4,"geometry.RatchetFemaleUwU":4,"geometry.swordtest":4,"geometry.thomas":4,"geometry.antichungus":4,"geometry.Jhongamer":4,"geometry.esbeon":4,"geometry.Arlekinrifle":4,"geometry.calamardo":4,"geometry.maids":4,"geometry.mikucubik":4,"geometry.SerekTheHare":4,"geometry.RatchetFemaleUwUv2":4,"geometry.pikachuu":4,"geometry.enderdragonwings":4,"geometry.birb":4,"geometry.BB8":4,"geometry.PiglinBrute":4,"geometry.drowned":4,"geometry.ratchet":4,"geometry.Rushia":4,"geometry.kirito5d":4,"geometry.Megumim":4,"geometry.DeadPool":4,"geometry.ElSalfontius":4,"geometry.alberteinstein4D":4,"geometry.kingbacksword":4,"geometry.toybonny":4,"geometry.SoraKH2":4,"geometry.NCRRanger":4,"geometry.Mario64":4,"geometry.honeylovelyrobots":5,"geometry.sfm1":5,"geometry.Girl_BunnyUWU":5,"geometry.humanoid.cgigirl":5,"geometry.Girl_Bunny_PERUWU":5,"geometry.mikecrackbebe":5,"geometry.Kanna":5,"geometry.ChuckECheese":5,"geometry.Scout-RED":5,"geometry.perfect_cell":5,"geometry.mordecai":5,"geometry.ExploradorNetherUpdate":5,"geometry.kgirls01":5,"geometry.Prototype24":5,"geometry.HulkBuster":5,"geometry.IronMk2":5,"geometry.kirisame_marisa":5,"geometry.kumiho":5,"geometry.flandre_scarlet":5,"geometry.remilia_scarlet":5,"geometry.cirno":5,"geometry.Luigi5D":5,"geometry.LetreroNoSimp":5,"geometry.Camera":5,"geometry.GoldKinght":5,"geometry.MoCreaturesTurkey":5,"geometry.MoCreaturesFox":5,"geometry.MoCreaturesDeer":5,"geometry.InkSansByNadaNaun":5,"geometry.gatito":5,"geometry.KnucklesTheEchidna":5,"geometry.EnderThicc":5,"geometry.EvilChicken":5,"geometry.EnderDragonGirl":5,"geometry.SlimeGirl":5,"geometry.Gumball":5,"geometry.Darwin":5,"geometry.Hytale":5,"geometry.Cameramurilo":5,"geometry.miguelruso":5,"geometry.HelenAngel":5,"geometry.Aqua":5,"geometry.arundav2":5,"geometry.gatitominerov2":5,"geometry.G41":5,"geometry.fallguy":5,"geometry.sirenaprojectskin":5,"geometry.sirenaprojectskin1":5,"geometry.AdultLink":5,"geometry.SimplePan":5,"geometry.faputa":5,"geometry.ZeroTails":5,"geometry.werecat":5,"geometry.kobold":5,"geometry.PS5Chan":5,"geometry.Naruto":5,"geometry.DFlogFlagChan":5,"geometry.DFlogFlagChanCape":5,"geometry.pennywise777":5,"geometry.pikachuuv2":5,"geometry.Sonic5D":5,"geometry.lucario5D":5,"geometry.Miau":5,"geometry.lxdgoleo":5,"geometry.ArlekinAsesino":5,"geometry.stonewarrior":5,"geometry.baphomet":5,"geometry.boneknight":5,"geometry.Debug":5,"geometry.gaiabee":5,"geometry.gaiamaid":5,"geometry.harpyWizard":5,"geometry.matango":5,"geometry.Oni":5,"geometry.succubus":5,"geometry.Valkyrie":5,"geometry.WereSheep":5,"geometry.LaughingJack":5,"geometry.kouteipengin":5,"geometry.Darkheart":5,"geometry.pandita":5,"geometry.demofurroxd":5,"geometry.astrokillerfp":5,"geometry.greenguspande":5,"geometry.dinogalaxy":5,"geometry.dinobackpack":5,"geometry.general24":5,"geometry.dragowhite":5,"geometry.doggyta":5,"geometry.ZeroTwo":5,"geometry.DemonioKawai":5,"geometry.arwing":5,"geometry.furrygirl5D":5,"geometry.gohma":5,"geometry.mermaidsbird":5,"geometry.mermaidsbirdpeinado1":5,"geometry.Amy5D":5,"geometry.MediumFenixGirl":5,"geometry.UzakiChan5D":5,"geometry.Rafito":5,"geometry.Shantae":6,"geometry.RaidenWolf":6,"geometry.faunaboy":6,"geometry.amongus":6,"geometry.amongushat":6,"geometry.amongusstraw":6,"geometry.amonguschild":6,"geometry.Astro4d":6,"geometry.amongcuernos":6,"geometry.dinosaurioXD":6,"geometry.SteveRico":6,"geometry.FLIPY":6,"geometry.SSBUEnderman":6,"geometry.Marselo5D":6,"geometry.SSBUMCKirby":6,"geometry.SSBUMCCreeper":6,"geometry.3DGolem":6,"geometry.vaporeonV2":6,"geometry.cofrecursed":6,"geometry.amongusgorrito":6,"geometry.Bencgz4d":6,"geometry.amongacompanado":6,"geometry.EggDog":6,"geometry.ItpsSpringsbonnies":6,"geometry.cheetah":6,"geometry.samoyedo":6,"geometry.ArlekinDemonio":6,"geometry.amongjason":6,"geometry.amonghuevo":6,"geometry.StartheWolf":6,"geometry.MCFemaleWolfHD":6,"geometry.MCGoat":6,"geometry.bunny2":6,"geometry.elegantdirt":6,"geometry.ALotOfMobsSkin":6,"geometry.gekkouga":6,"geometry.HDWingsHornAndEyes":6,"geometry.HDWingsHornAndEyesGirl":6,"geometry.HDWingsHornAndEyesGirlB":6,"geometry.OtherEarsAndTailGirl":6,"geometry.OtherEarsAndTail":6,"geometry.platanofornite":6,"geometry.meliodasasalto":6,"geometry.Arlekin117":6,"geometry.Mew":6,"geometry.OOTKidLink":6,"geometry.Mewtwo":6,"geometry.SuilSkinV2":6,"geometry.PolloLadron":6,"geometry.PerryElOrnitorrinco":6,"geometry.EndermanRaro":6,"geometry.ArlekinAkatsuki":6,"geometry.paimon":6,"geometry.GirlEnder":6,"geometry.dragonite":6,"geometry.AdultOoTLink":6,"geometry.SirenaPeinado":6,"geometry.Sirena":6,"geometry.SovietAxolot":6,"geometry.HumanoidAxolotl":6,"geometry.SCP035":6,"geometry.SCP001":6,"geometry.SCP250v":6,"geometry.IndevRana":6,"geometry.padoru":6,"geometry.PogChamp":6,"geometry.GirlIDKWhy":6,"geometry.Axolotl":6,"geometry.CuteMobAisha":6,"geometry.CuteMobBat":6,"geometry.CuteMobChicken":6,"geometry.CuteMobChillager":6,"geometry.CuteMobCow":6,"geometry.CuteMobGiffany":6,"geometry.CuteMobGigantGhast":6,"geometry.CuteMobNamelessKing":6,"geometry.CuteMobNecromancer":6,"geometry.CuteMobPanda":6,"geometry.CuteMobPig":6,"geometry.CuteMobPiglin":6,"geometry.CuteMobPiglinBrute":6,"geometry.CuteMobPillager":6,"geometry.CuteMobPolarBear":6,"geometry.CuteMobPrimsarineFoe":6,"geometry.CuteMobRavager":6,"geometry.CuteMobSakuya":6,"geometry.CuteMobSkeleton":6,"geometry.CuteMobSlime":6,"geometry.CuteMobSnowgolem":6,"geometry.CuteMobSquid":6,"geometry.CuteMobTurtle":6,"geometry.CuteMobVilerWitch":6,"geometry.CuteMobWindcaller":6,"geometry.CuteMobWraith":6,"geometry.CuteMobRabbit":6,"geometry.CuteMobHorse":6,"geometry.CuteMobCat":6,"geometry.CuteMobEnderDragon":6,"geometry.CuteMobGoat":6,"geometry.CuteMobBee":6,"geometry.CuteMobHoglin":7,"geometry.Amber5D":7,"geometry.BillChipher":7,"geometry.Cosmo":7,"geometry.KevArtsSnowman":7,"geometry.RaichuV2":7,"geometry.JahySama":7,"geometry.Cali":7,"geometry.Lenma":7,"geometry.Gura":7,"geometry.Ina":7,"geometry.Amelia":7,"geometry.protogen":7,"geometry.Snowman5D":7,"geometry.capahdv2":7,"geometry.Flaffy":7,"geometry.YoshiFachero":7,"geometry.DragonSkin4D":7,"geometry.Michiru":7,"geometry.Link3DS":7,"geometry.PuroTactico":7,"geometry.CapaHDSlimV3":7,"geometry.ExMermaidLamia":7,"geometry.AlienSkeleton":7,"geometry.BlueMaid":7,"geometry.greenmaid":7,"geometry.cowgirl":7,"geometry.cowmaid2":7,"geometry.cowmaid":7,"geometry.Coral":7,"geometry.Angelris":7,"geometry.AmongDrip":7,"geometry.DripSteve":7,"geometry.YoungLinkOOT3D":7,"geometry.Kanna5D":7,"geometry.Elizabeth5D":7,"geometry.Dream":7,"geometry.IronKnuckle":7,"geometry.RedGirlFirst3DModel":7,"geometry.SenkoSanSimple5D":7,"geometry.EmotionGuy":7,"geometry.SagiriIzumi5D":7,"geometry.AndanaBunny":7,"geometry.Aqua5D":7,"geometry.BF":7,"geometry.BigChungus":7,"geometry.Bonzi":7,"geometry.Chaos5D":7,"geometry.CharlesCalvin":7,"geometry.CPenguin":7,"geometry.Cucaracha":7,"geometry.Faputa4D":7,"geometry.GDBall":7,"geometry.GDBloque":7,"geometry.GDNave":7,"geometry.GDUFO":7,"geometry.Kinako5D":7,"geometry.Luna":7,"geometry.Nano":7,"geometry.Protogen2":7,"geometry.REDYael":7,"geometry.rounded":7,"geometry.Tappy":7,"geometry.Wheelchair":7,"geometry.DreamSkin4D":7,"geometry.Mash":7,"geometry.Nyack":7,"geometry.PapyrusCubic5D":7,"geometry.MamonoChan5D":7,"geometry.AlchemiaStoryCC1":7,"geometry.KonChan":7,"geometry.CreeperGirl5D":7,"geometry.FierceDeity":7,"geometry.cursedFlog":7,"geometry.LegendaryHeroWindWakerWeapons":7,"geometry.LegendaryHeroWindWakerStone":7,"geometry.LegendaryHeroWindWaker":7,"geometry.AndrextumadreCubic":7,"geometry.CarsAuto":7,"geometry.HytaleAndrex":7,"geometry.ShadowSkin4DS":7,"geometry.Leafeon":7,"geometry.LinkAwakening5D":7,"geometry.Kumatora":7,"geometry.Momiji5DChibi":7,"geometry.NekoRobot":7,"geometry.BunnyGirlGrey":7,"geometry.HomeroSimpson":7,"geometry.Mascotu":7,"geometry.DaftPunk":7,"geometry.Punk":7,"geometry.Yael4D2":7,"geometry.AndyUwU":7,"geometry.Amarillo":7,"geometry.Isaac":7,"geometry.QuetzalcoatlBlanco":7,"geometry.ElChavoDel8":7,"geometry.MikuNakano5D":7,"geometry.AmethystGolem":7,"geometry.GirlClothStyle1":7,"geometry.GirlClothStyle3":8,"geometry.GirlClothStyle2":8,"geometry.HappyMaskMan":8,"geometry.939":8,"geometry.VactricakingMissMinutes":8,"geometry.Vaporeon4D":8,"geometry.RoboProjecter":8,"geometry.TankTroop":8,"geometry.HDCuteGoatGirl":8,"geometry.Flygon4D":8,"geometry.WitherEffects":8,"geometry.BLDMBG":8,"geometry.PM":8,"geometry.FM":8,"geometry.RM":8,"geometry.SM":8,"geometry.CM":8,"geometry.CatM":8,"geometry.PapM":8,"geometry.AncestralGolem":8,"geometry.RealisticAnimations":8,"geometry.WalkingDogs":8,"geometry.AnimatedEnderDragon":8,"geometry.RealisticFace":8,"geometry.JiDemon":8,"geometry.Tanjiro5D":8,"geometry.DvaMekaVactricaKing":8,"geometry.MCPhantom":8,"geometry.Pachirisu4D":8,"geometry.null":8}